perf/__init__.py
perf/client.py
perf/exceptions.py
perf/types.py
perf_sdk-0.1.1.dist-info/METADATA
perf_sdk-0.1.1.dist-info/WHEEL
perf_sdk-0.1.1.dist-info/RECORD
